{
  "subject": "전기기능사",
  "unit": "전기이론",
  "set": 14,
  "slides": [
    {
      "id": 1,
      "title": "발전기끼리 손잡고 달리기",
      "content": "두 대의 발전기가 함께 일할 때 전압의 박자(위상)가 맞지 않으면 서로 힘겨루기를 하느라 쓸데없는 전류가 흘러요. 이때는 여자 전류를 조절해서 전압의 높낮이를 딱 맞춰줘야 두 발전기가 사이좋게 전기를 만들어냅니다.",
      "visual": "⚙️ 동기 발전기, 🔄 위상차, ⚡ 무효 순환 전류",
      "exam_point": "위상차가 생기면 '무효 순환 전류(무효 횡류)'가 흐른다는 점이 시험의 단골 정답이에요!",
      "image": "/summaries/전기기능사/slide_전기이론_14_1.webp"
    },
    {
      "id": 2,
      "title": "전류가 늦으면 힘이 빠져요!",
      "content": "발전기에서 전류가 전압보다 90도 늦게 따라오면 발전기 내부의 자석 힘을 갉아먹는 현상이 발생해요. 이걸 '감자 작용'이라고 하는데, 마치 자석의 기운이 쏙 빠져버리는 것과 같답니다.",
      "visual": "📉 지상 전류, 🧊 감자 작용, 🧲 전기자 반작용",
      "exam_point": "90도 뒤진 전류(지상)는 자속을 감소시키는 '감자 작용'을 일으킨다는 것을 기억하세요!",
      "image": "/summaries/전기기능사/slide_전기이론_14_2.webp"
    },
    {
      "id": 3,
      "title": "엄지손가락이 가리키는 곳은 N극",
      "content": "코일에 흐르는 전류의 방향을 알면 자석의 극성을 알 수 있어요. 오른손으로 코일을 감싸 쥐었을 때, 쭉 편 엄지손가락이 가리키는 방향이 바로 자석의 N극이 되는 마법 같은 법칙이죠.",
      "visual": "🖐️ 오른손 법칙, ➰ 솔레노이드, 🧭 N극 찾기",
      "exam_point": "솔레노이드 문제에서 오른손 엄지는 무조건 N극의 방향을 정답으로 가리킵니다!",
      "image": "/summaries/전기기능사/slide_전기이론_14_3.webp"
    },
    {
      "id": 4,
      "title": "전압과 전류의 달리기 경주",
      "content": "교류 회로에서 전압과 전류는 항상 같이 달리지 않아요. 전류 수식에 '-π/6' 같은 숫자가 붙어있다면, 이건 전류가 전압보다 30도 늦게 출발했다는 지연 신호랍니다.",
      "visual": "🏃 전압 vs 전류, 📏 위상차 30도, ⏱️ 지상(뒤짐)",
      "exam_point": "π/6은 30도! 부호가 마이너스(-)면 전류가 전압보다 뒤진다는 뜻입니다.",
      "image": "/summaries/전기기능사/slide_전기이론_14_4.webp"
    },
    {
      "id": 5,
      "title": "전압이 깎이는 비율 계산법",
      "content": "전기가 전선을 타고 이동할 때 저항과 리액턴스라는 장애물을 만나 전압이 조금 낮아져요. 이걸 '전압 변동률'이라고 하는데, 공식만 알면 도착지에서 얼마나 힘이 빠졌는지 바로 알 수 있죠.",
      "visual": "📈 전압 변동률, ⚡ p cosθ + q sinθ, 📉 전압 강하",
      "exam_point": "공식 ε = p cosθ + q sinθ를 외우세요. 역률이 0.8이면 sin값은 0.6이라는 점이 힌트!",
      "image": "/summaries/전기기능사/slide_전기이론_14_5.webp"
    },
    {
      "id": 6,
      "title": "전기 흐름의 방패, 임피던스",
      "content": "저항(R)과 인덕턴스(L)는 힘을 합쳐 전기의 흐름을 방해하는 '임피던스'라는 큰 방패를 만들어요. 이 방패의 크기를 피타고라스 정리처럼 계산하면 회로에 흐르는 진짜 전류를 구할 수 있답니다.",
      "visual": "🛡️ 임피던스 Z, 📐 피타고라스 정리, ⚡ I = V/Z",
      "exam_point": "임피던스 Z = √(R² + X²)를 먼저 구하고, 전압을 Z로 나누면 전류가 나옵니다!",
      "image": "/summaries/전기기능사/slide_전기이론_14_6.webp"
    },
    {
      "id": 7,
      "title": "마법의 전압 바구니, 콘덴서",
      "content": "콘덴서는 전기를 잠시 담아두는 바구니 같아요. 이 바구니에 담긴 에너지는 전압을 높일수록 전압의 제곱만큼 엄청나게 커져서 보관된답니다.",
      "visual": "🔋 콘덴서, ⚡ 에너지 W = 1/2 CV², 🧺 전기 저장",
      "exam_point": "에너지 공식 W = 1/2 CV²에서 전압(V)에 반드시 제곱을 해주는 것이 핵심입니다!",
      "image": "/summaries/전기기능사/slide_전기이론_14_7.webp"
    },
    {
      "id": 8,
      "title": "맴돌이 전류의 낭비를 막아라!",
      "content": "철심 안에서 전기가 뱅글뱅글 돌며 열을 만드는 '와전류'는 에너지 도둑이에요. 이 도둑을 잡기 위해 철판을 얇게 썰어 겹겹이 쌓는 '성층' 방식을 사용해 전기의 통로를 끊어줍니다.",
      "visual": "🌀 와전류(Eddy Current), 🥞 성층 철심, 📉 손실 감소",
      "exam_point": "와전류손을 줄이는 방법은? 정답은 항상 '규소 강판'을 '성층'하는 것입니다!",
      "image": "/summaries/전기기능사/slide_전기이론_14_8.webp"
    },
    {
      "id": 9,
      "title": "전동기 회전 방향 바꾸기",
      "content": "선풍기 날개를 반대로 돌리고 싶다면 어떻게 할까요? 3상 전동기에서는 들어오는 전선 3개 중 아무거나 2개만 쓱 바꿔서 연결하면 회전 방향이 즉시 반대로 바뀐답니다.",
      "visual": "🔄 회전 방향 변경, 🔌 3선 중 2선 교체, ⚙️ 유도 전동기",
      "exam_point": "3상 유도 전동기의 역회전 방법은 '3선 중 2선의 접속을 바꾼다'를 찾으세요!",
      "image": "/summaries/전기기능사/slide_전기이론_14_9.webp"
    },
    {
      "id": 10,
      "title": "전선의 병렬 연결 주의사항",
      "content": "무거운 짐을 여러 명이 나누어 들듯 전선도 병렬로 연결해 큰 전류를 보낼 수 있어요. 하지만 이때 각 전선에 퓨즈를 따로 달면 한쪽이 끊겼을 때 다른 전선에 과부하가 걸려 불이 날 수 있으니 주의해야 해요.",
      "visual": "🛣️ 병렬 도로, 🚫 퓨즈 설치 금지, ⚠️ 과부하 위험",
      "exam_point": "전선의 병렬 사용 시 '각 전선에 퓨즈를 장착하지 말 것'이 가장 중요한 설치 기준입니다!",
      "image": "/summaries/전기기능사/slide_전기이론_14_10.webp"
    }
  ]
}