{
  "subject": "컴퓨터활용능력 2급",
  "unit": "[1과목] 데이터 표현 기술 및 소프트웨어 공학 기초",
  "set": 2,
  "slides": [
    {
      "id": 1,
      "style": "Expert",
      "image": "/summaries/컴퓨터활용능력 2급/_1과목__데이터_표현_기술_및_소프트웨어_공학_기초_2_slide_1.png",
      "emoji": "🌐",
      "title": "IoT: 만물 연결의 시작",
      "content": "모든 사물에 센서와 통신 기능을 넣어 인터넷에 연결하는 기술입니다. 사람 개입 없이 사물과 사물이 정보를 주고받아 지능형 환경을 구현합니다. 마치 모든 물건이 대화하는 세상과 같습니다.",
      "visual": "다양한 일상 사물(냉장고, 자동차, 스마트폰 등)이 서로 네트워크 선으로 연결되어 정보를 주고받는 모습. 중앙에 'IoT'라는 글자가 빛나고 있다.",
      "exam_point": "키워드: '모든 사물', '네트워크 연결', '소통', '센서'. IPv6과 연관 출제. 유비쿼터스와의 차이점 주의."
    },
    {
      "id": 2,
      "style": "Expert",
      "image": "/summaries/컴퓨터활용능력 2급/_1과목__데이터_표현_기술_및_소프트웨어_공학_기초_2_slide_2.png",
      "emoji": "🛣️",
      "title": "네트워크의 스마트한 교통경찰",
      "content": "라우터는 데이터가 목적지까지 가장 빠르고 효율적인 길을 찾아줍니다. 서로 다른 네트워크를 연결하는 내비게이션 역할을 합니다. 리피터는 약해진 신호를 증폭해 먼 거리까지 전달합니다.",
      "visual": "복잡한 도시의 도로망 위에 데이터 패킷이 흘러가고 있고, 한가운데 'Router'라는 표지판을 든 경찰관이 최적의 길을 안내하는 모습. 옆에는 신호를 증폭시키는 'Repeater' 장치가 있다.",
      "exam_point": "라우터: '최적의 경로', '다른 네트워크 연결'. 리피터: '신호 증폭', '거리 연장'. 허브: '단순 연결 집중 장치'. 게이트웨이: '프로토콜 다른 망 연결'."
    },
    {
      "id": 3,
      "style": "Expert",
      "image": "/summaries/컴퓨터활용능력 2급/_1과목__데이터_표현_기술_및_소프트웨어_공학_기초_2_slide_3.png",
      "emoji": "🏠",
      "title": "인터넷 속 우리집 주소, IP 주소",
      "content": "IP 주소는 인터넷 기기를 식별하는 고유 번호입니다. IPv4는 32비트 주소로 주소 고갈 문제가 있습니다. IPv6는 128비트 주소로 이를 해결하며 보안도 강화됩니다.",
      "visual": "전 세계 지도 위에 수많은 집들이 그려져 있고, 각 집에 숫자(IPv4)와 복잡한 문자(IPv6) 형태의 주소가 표시되어 있다. IPv6 주소 쪽이 훨씬 많고 넓게 퍼져 있다.",
      "exam_point": "IPv4: 32비트, 10진수, 마침표(.) 구분. IPv6: 128비트, 16진수, 콜론(:) 구분, 주소 부족 해결, 보안성, 호환성 우수."
    },
    {
      "id": 4,
      "style": "Expert",
      "image": "/summaries/컴퓨터활용능력 2급/_1과목__데이터_표현_기술_및_소프트웨어_공학_기초_2_slide_4.png",
      "emoji": "🏷️",
      "title": "IP 주소의 쉬운 이름, 도메인 네임",
      "content": "도메인 네임은 복잡한 IP 주소를 사람이 기억하기 쉽게 문자로 표현합니다. 전 세계적으로 유일해야 하며 공인기관을 통해 등록됩니다. DNS는 도메인과 IP 주소를 상호 변환해 줍니다.",
      "visual": "왼쪽에 복잡한 숫자 배열의 IP 주소(예: 203.241.10.12)가 있고, 오른쪽에 'naver.com'과 같은 도메인 네임이 있다. 중간에 DNS 서버가 번역기처럼 연결하고 있다.",
      "exam_point": "도메인 네임: '문자 형태', 'IP 주소 별명', '전 세계 유일', '등록 필요'. DNS: '도메인-IP 주소 변환 시스템'. KISA: 국내 도메인 관리."
    },
    {
      "id": 5,
      "style": "Expert",
      "image": "/summaries/컴퓨터활용능력 2급/_1과목__데이터_표현_기술_및_소프트웨어_공학_기초_2_slide_5.png",
      "emoji": "🎨",
      "title": "그림에 생명 불어넣기",
      "content": "렌더링은 3차원 물체에 명암, 색상, 질감을 입혀 사실감을 더하는 기법입니다. 뼈대 위에 살을 붙이는 과정과 같습니다. 안티앨리어싱은 이미지의 계단 현상을 부드럽게 처리합니다.",
      "visual": "왼쪽에는 뼈대만 있는 3D 모델이 있고, 오른쪽에는 명암, 색상, 질감이 완벽하게 표현된 사실적인 3D 이미지가 대비되어 있다. 아래에는 거친 계단 현상이 있는 글자와 부드럽게 처리된 글자가 비교되어 있다.",
      "exam_point": "렌더링: '3차원', '명암/색상/질감 추가', '사실감'. 안티앨리어싱: '계단 현상 제거', '부드럽게 표현'."
    },
    {
      "id": 6,
      "style": "Expert",
      "image": "/summaries/컴퓨터활용능력 2급/_1과목__데이터_표현_기술_및_소프트웨어_공학_기초_2_slide_6.png",
      "emoji": "📝",
      "title": "컴퓨터의 언어, 문자 코드",
      "content": "ASCII는 PC와 데이터 통신용 7비트(128자) 코드입니다. 확장 ASCII는 8비트(256자)입니다. 유니코드는 전 세계 문자를 2바이트(16비트, 65,536자)로 표현하는 국제 표준 코드입니다.",
      "visual": "다양한 언어의 문자들(한글, 영어, 한자, 아랍어 등)이 한 화면에 모여 있고, 그 위로 'Unicode'라는 큰 글자가 모든 문자를 포괄하는 모습을 보여준다. 한쪽에는 'ASCII (A-Z, a-z, 0-9)'가 작은 범위로 표시되어 있다.",
      "exam_point": "ASCII: 7비트(128자), PC/데이터 통신. 확장 ASCII: 8비트(256자). 유니코드: 16비트(2바이트), '전 세계 문자', '국제 표준'. BCD: 6비트. EBCDIC: 8비트, 대형 컴퓨터용."
    },
    {
      "id": 7,
      "style": "Expert",
      "image": "/summaries/컴퓨터활용능력 2급/_1과목__데이터_표현_기술_및_소프트웨어_공학_기초_2_slide_7.png",
      "emoji": "🎁",
      "title": "공짜? 체험판? 소프트웨어 종류",
      "content": "셰어웨어는 특정 기능이나 기간을 제한해 무료 배포하는 체험판입니다. 마음에 들면 유료 구매를 유도합니다. 프리웨어는 누구나 제한 없이 완전 무료로 쓸 수 있는 소프트웨어입니다.",
      "visual": "한쪽에는 'Shareware'라고 쓰인 상자에 '30일 체험'이나 '일부 기능 제한' 스티커가 붙어있는 모습. 다른 한쪽에는 'Freeware'라고 쓰인 상자가 활짝 열려 있고, 누구나 자유롭게 사용하는 모습.",
      "exam_point": "셰어웨어: '기능/기간 제한', '체험판', '유료 전환 유도'. 프리웨어: '완전 무료', '자유 사용'. 상용 SW: '유료'. 오픈 소스: '소스 공개', '자유 수정/재배포'."
    },
    {
      "id": 8,
      "style": "Expert",
      "image": "/summaries/컴퓨터활용능력 2급/_1과목__데이터_표현_기술_및_소프트웨어_공학_기초_2_slide_8.png",
      "emoji": "🕶️",
      "title": "새로운 세상, 가상과 현실의 만남",
      "content": "가상 현실(VR)은 컴퓨터 그래픽으로 100% 가상 세계를 만들어 현실처럼 체험합니다. 증강 현실(AR)은 실제 현실 배경에 가상 정보를 겹쳐 보여주는 기술입니다.",
      "visual": "왼쪽에는 VR 헤드셋을 착용한 사람이 완벽하게 가상 게임 세계에 몰입해 있는 모습. 오른쪽에는 스마트폰 화면을 통해 실제 길거리에 가상의 캐릭터가 나타나는 AR 게임(포켓몬고 연상) 장면.",
      "exam_point": "VR: '100% 가상 세계', '몰입감', 'HMD'. AR: '실제 현실 + 가상 정보', '포켓몬고'. 3차원 기법이 핵심."
    },
    {
      "id": 9,
      "style": "Expert",
      "image": "/summaries/컴퓨터활용능력 2급/_1과목__데이터_표현_기술_및_소프트웨어_공학_기초_2_slide_9.png",
      "emoji": "📈",
      "title": "데이터 처리 방식: 진화의 과정",
      "content": "초기에는 데이터를 모아 한꺼번에 처리하는 일괄 처리 방식이었습니다. 이후 실시간으로 즉시 처리하는 실시간 처리로 발전했습니다. 현재는 여러 컴퓨터에 나눠 처리하는 분산 처리가 보편적입니다.",
      "visual": "시간의 흐름에 따라 데이터 처리 방식이 발전하는 인포그래픽. '일괄 처리'는 우편함에 쌓인 편지를 한 번에 처리하는 모습, '실시간 처리'는 은행 ATM에서 즉시 거래하는 모습, '분산 처리'는 여러 컴퓨터가 유기적으로 연결되어 작업하는 모습.",
      "exam_point": "순서: '일괄 처리' → '실시간 처리' → '분산 처리'. 일괄: '급여/수도 요금'. 실시간: '은행 입출금'. 분산: '클라우드 컴퓨팅'. 시분할 처리도 중간 단계로 기억."
    },
    {
      "id": 10,
      "style": "Expert",
      "image": "/summaries/컴퓨터활용능력 2급/_1과목__데이터_표현_기술_및_소프트웨어_공학_기초_2_slide_10.png",
      "emoji": "🚨",
      "title": "정보 보안 위협: 스니핑 & 스푸핑",
      "content": "스니핑은 네트워크 패킷을 몰래 엿보아 정보를 탈취하는 도청 행위입니다. 스푸핑은 신뢰할 수 있는 IP인 척 위장하여 접근하는 기만 행위입니다. 둘 다 위험한 사이버 공격입니다.",
      "visual": "네트워크 선을 따라 흐르는 데이터 패킷을 해커가 몰래 돋보기로 엿보는 'Sniffing' 그림과, 마스크를 쓴 해커가 다른 사람의 얼굴을 한 가면을 쓰고 시스템에 접근하는 'Spoofing' 그림을 대비시켜 표현한다.",
      "exam_point": "스니핑: '엿보기', '도청', '패킷 가로채기'. 스푸핑: '위장', '속이기', 'IP/메일 주소 변조'. 키로거: '키보드 입력 기록'. 백도어: '뒷문 악용'."
    }
  ]
}