[
  {
    "number": 3,
    "question": "용해, 용접, 담금질, 가열 등에 가장 적합한 가열방식은?",
    "options": [
      "복사가열",
      "유도가열",
      "저항가열",
      "유전가열"
    ],
    "answer": 2,
    "pdf": "전기공사산업기사20180915(교사용).pdf",
    "page": 1
  },
  {
    "number": 12,
    "question": "고주파 유전가열에서 피열물의 단위 체적당 소비전력 [W/cm³]은? (단, E[V/cm]는 고주파 전계, δ는 유전체 손실각, f는 주파수, εₛ는 비유전율이다.)",
    "options": [
      "5/9 * E * f * εs * tanδ * 10^-9",
      "5/9 * E * f * εs * tanδ * 10^-10",
      "5/9 * E * f * εs * tanδ * 10^-8",
      "5/9 * E * f * εs * tanδ * 10^-12"
    ],
    "answer": 4,
    "pdf": "전기공사산업기사20180915(교사용).pdf",
    "page": 1
  },
  {
    "number": 16,
    "question": "플라즈마 용접의 특징이 아닌 것은?",
    "options": [
      "비드(bead)폭이 좁고 용입이 깊다.",
      "용접속도가 빠르고 균일한 용접이 된다.",
      "가스의 보호가 충분하여, 토치의 구조가 간단하다.",
      "플라즈마 아크의 에너지 밀도가 커서 안정도가 커서 안정도가 높다."
    ],
    "answer": 3,
    "pdf": "전기공사산업기사20180915(교사용).pdf",
    "page": 1
  },
  {
    "number": 3,
    "question": "전기가열 방식에 대한 설명으로 틀린 것은?",
    "options": [
      "저항가열은 줄열을 이용한 가열방식이다.",
      "유도가열은 표면 담금질 등의 열처리에 이용되는 방식이다.",
      "유전가열은 와전류손과 히스테리시스손에 의한 가열방식이다.",
      "아크가열은 전극사이에 발생하는 아크열을 이용한 가열방식이다."
    ],
    "answer": 3,
    "year": "2019",
    "pdf": "전기공사산업기사20190303(교사용).pdf",
    "page": 1
  },
  {
    "number": 4,
    "question": "엘리베이터용 전동기에 대한 설명으로 틀린 것은?",
    "options": [
      "관성모멘트가 작아야 한다.",
      "기동토크가 큰 것이 요구된다.",
      "플라이휠 효과($GD^2$)가 커야 한다.",
      "가속도의 변화율이 적어야 한다."
    ],
    "answer": 3,
    "year": "2019",
    "pdf": "전기공사산업기사20190303(교사용).pdf",
    "page": 1
  },
  {
    "number": 8,
    "question": "유도가열과 유전가열의 공통된 특성은?",
    "options": [
      "도체만을 가열한다.",
      "선택가열이 가능하다.",
      "절연체만을 가열한다.",
      "직류를 사용할 수 없다."
    ],
    "answer": 4,
    "year": "2019",
    "pdf": "전기공사산업기사20190303(교사용).pdf",
    "page": 1
  },
  {
    "number": 11,
    "question": "고주파 유전가열을 응용한 사항으로 틀린 것은?",
    "options": [
      "고무의 가황",
      "합판의 건조, 접착",
      "플라스틱의 성형과 비닐막 접착",
      "강재의 표면 담금질"
    ],
    "answer": 4,
    "year": "2019",
    "pdf": "전기공사산업기사20190303(교사용).pdf",
    "page": 1
  },
  {
    "number": 81,
    "question": "중선선 다중접지식의 것으로 전로에 지락이 생겼을 때에 2초 이내에 자동적으로 이를 전로로부터 차단하는 장치가 되어 있는 $22.9 kV$ 가공전선로를 상부 조영재의 위쪽에서 접근상태로 시설하는 경우, 가공전선과 건조물과의 이격거리는 몇 $m$ 이상이어야 하는가? (단, 전선으로는 나전선을 사용한다고 한다.)",
    "options": [
      "1.2",
      "1.5",
      "2.5",
      "3.0"
    ],
    "answer": 4,
    "year": "2019",
    "pdf": "전기공사산업기사20190303(교사용).pdf",
    "page": 6
  },
  {
    "number": 87,
    "question": "건조한 장소로서 전개된 장소에 한하여 시설할 수 있는 고압 옥내배선의 방법은?",
    "options": [
      "금속관 공사",
      "애자사용 공사",
      "가요전선관 공사",
      "합성수지관 공사"
    ],
    "answer": 2,
    "year": "2019",
    "pdf": "전기공사산업기사20190303(교사용).pdf",
    "page": 6
  },
  {
    "number": 10,
    "question": "교번 자계 중에서 도전성 물질 내에 생기는 와류손과 히스테리시스손에 의한 가열 방식은?",
    "options": [
      "저항가열",
      "유도가열",
      "유전가열",
      "아크가열"
    ],
    "answer": 2,
    "year": "2019",
    "pdf": "전기공사산업기사20190427(교사용).pdf",
    "page": 1
  },
  {
    "number": 14,
    "question": "동력 전달 효율이 $78.4\\%$인 권상기로 $30\\text{t}$의 하중을 매분 $4\\text{m}$의 속도로 끌어 올리는 데 필요한 동력은 약 몇 $\\text{kW}$인가?",
    "options": [
      "14",
      "18",
      "21",
      "25"
    ],
    "answer": 4,
    "year": "2019",
    "pdf": "전기공사산업기사20190427(교사용).pdf",
    "page": 1
  },
  {
    "number": 3,
    "question": "고주파 유전가열의 용도로 적합하지 않은 것은?",
    "options": [
      "목재의 접착",
      "플라스틱 성형",
      "비닐의 접착",
      "금속의 열처리"
    ],
    "answer": 4,
    "year": "2019",
    "pdf": "전기공사산업기사20190921(교사용).pdf",
    "page": 1
  },
  {
    "number": 38,
    "question": "출력 20kW의 전동기로서 총 양정 10m, 펌프효율 0.75일 때 양수량은 약 몇 $m^3/min$ 인가?",
    "options": [
      "9.18",
      "9.85",
      "10.31",
      "11.02"
    ],
    "answer": 1,
    "year": "2019",
    "pdf": "전기공사산업기사20190921(교사용).pdf",
    "page": 3
  },
  {
    "number": 90,
    "question": "$66kV$ 가공전선이 건조물과 제1차 접근상태로 시설되는 경우 가공전선과 건조물 사이의 이격거리는 최소 몇 $m$ 이상이어야 하는가? (단, 전선은 나전선으로 한다.)",
    "options": [
      "3.0",
      "3.2",
      "3.4",
      "3.6"
    ],
    "answer": 4,
    "year": "2019",
    "pdf": "전기공사산업기사20190921(교사용).pdf",
    "page": 6
  },
  {
    "number": 5,
    "question": "다음 중 유도가열은 어떤 것을 이용한 것인가?",
    "options": [
      "복사열",
      "아크열",
      "와전류손",
      "유전체손"
    ],
    "answer": 3,
    "year": "2020",
    "pdf": "전기공사산업기사20200606(교사용).pdf",
    "page": 1
  },
  {
    "number": 13,
    "question": "방전용접 중 불활성 가스용접에 쓰이는 불활성 가스는?",
    "options": [
      "아르곤",
      "수소",
      "산소",
      "질소"
    ],
    "answer": 1,
    "year": "2020",
    "pdf": "전기공사산업기사20200606(교사용).pdf",
    "page": 1
  },
  {
    "number": 19,
    "question": "목재의 건조, 베니어판 등의 합판에서의 접착 건조, 약품의 건조 등에 적합한 전기 건조 방식은?",
    "options": [
      "아크 건조",
      "고주파 건조",
      "적외선 건조",
      "자외선 건조"
    ],
    "answer": 2,
    "year": "2020",
    "pdf": "전기공사산업기사20200606(교사용).pdf",
    "page": 1
  },
  {
    "number": 3,
    "question": "목재건조에 적합한 가열 방식은?",
    "options": [
      "저항가열",
      "적외선 가열",
      "유전가열",
      "유도가열"
    ],
    "answer": 3,
    "year": "2020",
    "pdf": "전기공사산업기사20200822(교사용).pdf",
    "page": 1
  },
  {
    "number": 12,
    "question": "초음파 용접의 특징으로 옳지 않은 것은?",
    "options": [
      "전기 저항 용접에 비하여 표면의 전처리가 간단하다.",
      "가열을 필요로 하지 않는다.",
      "냉간 압접 등에 비하여 접합부 표면의 변형이 적다.",
      "고체상태에서의 용접이므로 열적 영향이 크다."
    ],
    "answer": 4,
    "year": "2020",
    "pdf": "전기공사산업기사20200822(교사용).pdf",
    "page": 1
  },
  {
    "number": 16,
    "question": "평행평판 전극 사이에 유전체인 피열물을 삽입하고 고주파 전계를 인가하면 피열물 내 유전체손이 발생하여 가열되는 방식은?",
    "options": [
      "저항가열",
      "유도가열",
      "유전가열",
      "원자수소가열"
    ],
    "answer": 3,
    "year": "2020",
    "pdf": "전기공사산업기사20200822(교사용).pdf",
    "page": 1
  },
  {
    "number": 17,
    "question": "권상하중 10t, 매분 24m/min의 속도로 물체를 올리는 권상용 전동기의 용량(kW)은 약 얼마인가? (단, 전동기를 포함한 기중기의 효율은 65%이다.)",
    "options": [
      "41",
      "73",
      "60",
      "97"
    ],
    "answer": 3,
    "year": "2020",
    "pdf": "전기공사산업기사20200822(교사용).pdf",
    "page": 1
  },
  {
    "number": 3,
    "question": "초음파 용접의 특징으로 틀린 것은?",
    "options": [
      "표면의 전처리가 간단하다.",
      "가열을 필요로 하지 않는다.",
      "이종 금속의 용접이 가능하다.",
      "고체상태에서의 용접이므로 열적 영향이 크다."
    ],
    "answer": 4,
    "pdf": "전기공사산업기사20140525(교사용).pdf",
    "page": 1,
    "round_info": "전기공사산업기사20140525(교사용)",
    "choices": [
      "표면의 전처리가 간단하다.",
      "가열을 필요로 하지 않는다.",
      "이종 금속의 용접이 가능하다.",
      "고체상태에서의 용접이므로 열적 영향이 크다."
    ]
  },
  {
    "number": 6,
    "question": "기중기로 150[t]의 하중을 2[m/min]의 속도로 권상시킬 때 필요한 전동기의 용량[kW]은 약 얼마인가?(단, 기계효율은 70[%]이다.)",
    "options": [
      "70",
      "80",
      "90",
      "100"
    ],
    "answer": 1,
    "pdf": "전기공사산업기사20140525(교사용).pdf",
    "page": 1,
    "round_info": "전기공사산업기사20140525(교사용)",
    "choices": [
      "70",
      "80",
      "90",
      "100"
    ]
  },
  {
    "number": 10,
    "question": "다음 중 전기로의 가열방식이 아닌 것은?",
    "options": [
      "저항가열",
      "유전가열",
      "유도가열",
      "아크가열"
    ],
    "answer": 2,
    "pdf": "전기공사산업기사20140525(교사용).pdf",
    "page": 1,
    "round_info": "전기공사산업기사20140525(교사용)",
    "choices": [
      "저항가열",
      "유전가열",
      "유도가열",
      "아크가열"
    ]
  },
  {
    "number": 13,
    "question": "불활성 가스 용접에서 아르곤 가스가 헬륨보다 널리 사용되는 이유로 틀린 것은?",
    "options": [
      "전리 전압이 낮으므로 아크의 발생과 유지가 쉽다.",
      "피포작용이 강하여 기류가 견고하다.",
      "용접면의 산화방지 효과가 크다.",
      "가스 필요량이 적으며 가격이 저렴하다."
    ],
    "answer": 3,
    "pdf": "전기공사산업기사20140525(교사용).pdf",
    "page": 1,
    "round_info": "전기공사산업기사20140525(교사용)",
    "choices": [
      "전리 전압이 낮으므로 아크의 발생과 유지가 쉽다.",
      "피포작용이 강하여 기류가 견고하다.",
      "용접면의 산화방지 효과가 크다.",
      "가스 필요량이 적으며 가격이 저렴하다."
    ]
  },
  {
    "number": 16,
    "question": "단면적 S[m²]의 파이프를 θ로 경사시켜서 비중 ρ인 액체를 Q[m³/s]의 유량으로 양정 H[m]까지 끌어올린다고 할 때 액체 펌프에 요하는 소요동력 P[kW]는?",
    "options": [
      "P = ρHQs",
      "P = 9.8ρHQs",
      "P = ρHQ",
      "P = 9.8ρHQ"
    ],
    "answer": 4,
    "pdf": "전기공사산업기사20140525(교사용).pdf",
    "page": 1,
    "round_info": "전기공사산업기사20140525(교사용)",
    "choices": [
      "P = ρHQs",
      "P = 9.8ρHQs",
      "P = ρHQ",
      "P = 9.8ρHQ"
    ]
  },
  {
    "number": 99,
    "question": "용접변압기의 1차측 전로의 대지전압은 몇 V 이하이어야 하는가?",
    "options": [
      "200",
      "250",
      "300",
      "600"
    ],
    "answer": 3,
    "pdf": "전기공사산업기사20140525(교사용).pdf",
    "page": 7,
    "round_info": "전기공사산업기사20140525(교사용)",
    "choices": [
      "200",
      "250",
      "300",
      "600"
    ]
  },
  {
    "number": 3,
    "question": "금속의 표면 담금질에 가장 적합한 가열은?",
    "options": [
      "적외선 가열",
      "유도 가열",
      "유전 가열",
      "저항 가열"
    ],
    "answer": 2,
    "pdf": "전기공사산업기사20140920(교사용).pdf",
    "page": 1,
    "round_info": "전기공사산업기사20140920(교사용)",
    "choices": [
      "적외선 가열",
      "유도 가열",
      "유전 가열",
      "저항 가열"
    ]
  },
  {
    "number": 17,
    "question": "권상하중 40t, 권상속도 12m/min의 기중기용 전동기의 용량은 약 몇 kW인가? (단, 전동기를 포함한 기중기의 효율은 60%이다.)",
    "options": [
      "800",
      "278.9",
      "189.8",
      "130.7"
    ],
    "answer": 4,
    "pdf": "전기공사산업기사20140920(교사용).pdf",
    "page": 1,
    "round_info": "전기공사산업기사20140920(교사용)",
    "choices": [
      "800",
      "278.9",
      "189.8",
      "130.7"
    ]
  },
  {
    "number": 8,
    "question": "아크 용접기는 어떤 원리를 이용한 것인가?",
    "options": [
      "주울 열",
      "수하특성",
      "유전체 손",
      "히스테리시스 손"
    ],
    "answer": 2,
    "pdf": "전기공사산업기사20150308(교사용).pdf",
    "page": 1,
    "round_info": "전기공사산업기사20150308(교사용)",
    "choices": [
      "주울 열",
      "수하특성",
      "유전체 손",
      "히스테리시스 손"
    ]
  },
  {
    "number": 15,
    "question": "전류에 의한 옴[Ω]손을 이용하여 가열하는 것은?",
    "options": [
      "복사가열",
      "유전가열",
      "유도가열",
      "저항가열"
    ],
    "answer": 4,
    "pdf": "전기공사산업기사20150308(교사용).pdf",
    "page": 1,
    "round_info": "전기공사산업기사20150308(교사용)",
    "choices": [
      "복사가열",
      "유전가열",
      "유도가열",
      "저항가열"
    ]
  },
  {
    "number": 9,
    "question": "용접용 전원의 특성은 부하가 급히 증가할 때 전압은?",
    "choices": [
      "일정하다",
      "급히 상승한다.",
      "급히 강하한다.",
      "서서히 상승한다."
    ],
    "answer": 3,
    "pdf": "전기공사산업기사20150531(교사용).pdf",
    "page": 1,
    "round_info": "전기공사산업기사20150531(교사용)"
  },
  {
    "number": 10,
    "question": "권상하중 10,000kg, 권상속도 5m/min의 기중기용 전동기 용량은 약 몇 kW인가? (단, 전동기를 포함한 기중기의 효율은 80%라 한다.)",
    "choices": [
      "7.5",
      "8.3",
      "10.2",
      "14.3"
    ],
    "answer": 3,
    "pdf": "전기공사산업기사20150531(교사용).pdf",
    "page": 1,
    "round_info": "전기공사산업기사20150531(교사용)"
  },
  {
    "number": 14,
    "question": "공구, 기계부품, 전기기구 부품 등의 납땜 작업에 널리 사용되는 용접은?",
    "choices": [
      "유도 용접",
      "심 용접",
      "프로젝션 용접",
      "점 용접"
    ],
    "answer": 1,
    "pdf": "전기공사산업기사20150531(교사용).pdf",
    "page": 1,
    "round_info": "전기공사산업기사20150531(교사용)"
  },
  {
    "number": 17,
    "question": "엘리베이터용 전동기에 대한 설명으로 틀린 것은?",
    "choices": [
      "기동토크가 큰 것이 요구된다.",
      "플라이휠 효과(GD²)가 커야 한다.",
      "관성 모멘트가 작아야 한다.",
      "유도전동기도 엘리베이터에 사용된다."
    ],
    "answer": 2,
    "pdf": "전기공사산업기사20150531(교사용).pdf",
    "page": 1,
    "round_info": "전기공사산업기사20150531(교사용)"
  },
  {
    "number": 88,
    "question": "건조한 장소에 시설하는 애자사용 공사로서 사용전압이 440V인 경우 전선과 조영재와의 이격거리는 최소 몇 cm 이상이어야 하는가?",
    "options": [
      "2.5",
      "3.5",
      "4.5",
      "5.5"
    ],
    "answer": 1,
    "pdf": "전기공사산업기사20150531(교사용).pdf",
    "page": 6,
    "round_info": "전기공사산업기사20150531(교사용)",
    "choices": [
      "2.5",
      "3.5",
      "4.5",
      "5.5"
    ]
  },
  {
    "number": 6,
    "question": "비닐막 등의 접착에 주로 사용하는 가열 방식은?",
    "options": [
      "저항 가열",
      "유도 가열",
      "아크 가열",
      "유전 가열"
    ],
    "answer": 4,
    "pdf": "전기공사산업기사20150919(교사용).pdf",
    "page": 1,
    "round_info": "전기공사산업기사20150919(교사용)",
    "choices": [
      "저항 가열",
      "유도 가열",
      "아크 가열",
      "유전 가열"
    ]
  },
  {
    "number": 15,
    "question": "전구의 필라멘트나 열전대 용접에 알맞은 방법은?",
    "options": [
      "점 용접",
      "돌기 용접",
      "심 용접",
      "불활성 용접"
    ],
    "answer": 1,
    "pdf": "전기공사산업기사20150919(교사용).pdf",
    "page": 1,
    "round_info": "전기공사산업기사20150919(교사용)",
    "choices": [
      "점 용접",
      "돌기 용접",
      "심 용접",
      "불활성 용접"
    ]
  },
  {
    "number": 85,
    "question": "사용전압이 35000V 이하인 특별고압 가공전선이 건조물과 제 2차 접근상태로 시설되는 경우, 특별고압 가공전선로의 보안 공사는?",
    "options": [
      "고압 보안공사",
      "제 1종 특고압 보안공사",
      "제 2종 특고압 보안공사",
      "제 3종 특고압 보안공사"
    ],
    "answer": 3,
    "pdf": "전기공사산업기사20150919(교사용).pdf",
    "page": 6,
    "round_info": "전기공사산업기사20150919(교사용)",
    "choices": [
      "고압 보안공사",
      "제 1종 특고압 보안공사",
      "제 2종 특고압 보안공사",
      "제 3종 특고압 보안공사"
    ]
  },
  {
    "number": 7,
    "question": "간접식 저항가열에 사용되는 발열체의 필요조건이 아닌 것은?",
    "options": [
      "내열성이 클 것",
      "내식성이 클 것",
      "저항률이 비교적 크고 온도계수가 작을 것",
      "발열체의 최고온도가 가열온도보다 낮을 것"
    ],
    "answer": 4,
    "pdf": "전기공사산업기사20160306(교사용).pdf",
    "page": 1,
    "round_info": "전기공사산업기사20160306(교사용)",
    "choices": [
      "내열성이 클 것",
      "내식성이 클 것",
      "저항률이 비교적 크고 온도계수가 작을 것",
      "발열체의 최고온도가 가열온도보다 낮을 것"
    ]
  },
  {
    "number": 8,
    "question": "적외선 전구를 사용하는 건조과정에서 건조에 유효한 파장인 1~4[μm]의 방사파를 얻기 위하여 적외선 전구의 필라멘트 온도(°K) 범위는?",
    "options": [
      "1800 ~ 2200",
      "2200 ~ 2500",
      "2800 ~ 3000",
      "2800 ~ 3200"
    ],
    "answer": 2,
    "pdf": "전기공사산업기사20160306(교사용).pdf",
    "page": 1,
    "round_info": "전기공사산업기사20160306(교사용)",
    "choices": [
      "1800 ~ 2200",
      "2200 ~ 2500",
      "2800 ~ 3000",
      "2800 ~ 3200"
    ]
  },
  {
    "number": 12,
    "question": "자동차 등 차량공업, 기계 및 전기 기계기구, 기타 금속제품의 도장을 건조하는데 주로 이용되는 가열방식은?",
    "options": [
      "저항 가열",
      "유도 가열",
      "고주파 가열",
      "적외선 가열"
    ],
    "answer": 4,
    "pdf": "전기공사산업기사20160306(교사용).pdf",
    "page": 1,
    "round_info": "전기공사산업기사20160306(교사용)",
    "choices": [
      "저항 가열",
      "유도 가열",
      "고주파 가열",
      "적외선 가열"
    ]
  },
  {
    "number": 13,
    "question": "제품제조 과정에서의 화학 반응식이 다음과 같은 전기에의 가열 방식은? [SiO2 + 3C → SiC + 2CO]",
    "options": [
      "유전가열",
      "유도가열",
      "간접저항가열",
      "직접저항가열"
    ],
    "answer": 4,
    "pdf": "전기공사산업기사20160306(교사용).pdf",
    "page": 1,
    "round_info": "전기공사산업기사20160306(교사용)",
    "choices": [
      "유전가열",
      "유도가열",
      "간접저항가열",
      "직접저항가열"
    ]
  },
  {
    "number": 14,
    "question": "저항 가열은 어떤 원리를 이용한 것인가?",
    "options": [
      "줄열",
      "아크손",
      "유전체손",
      "히스테리시스손"
    ],
    "answer": 1,
    "pdf": "전기공사산업기사20160306(교사용).pdf",
    "page": 1,
    "round_info": "전기공사산업기사20160306(교사용)",
    "choices": [
      "줄열",
      "아크손",
      "유전체손",
      "히스테리시스손"
    ]
  },
  {
    "number": 94,
    "question": "사용전압이 22900[V]인 가공전선이 건조물과 제2차 접근상태로 시설되는 경우에 이 특고압 가공전선의 보안공사는 어떤 종류의 보안공사로 하여야 하는가?",
    "options": [
      "① 고압 보안공사",
      "② 제1종 특고압 보안공사",
      "③ 제2종 특고압 보안공사",
      "④ 제3종 특고압 보안공사"
    ],
    "answer": 3,
    "pdf": "전기공사산업기사20160306(교사용).pdf",
    "page": 6,
    "round_info": "전기공사산업기사20160306(교사용)",
    "choices": [
      "① 고압 보안공사",
      "② 제1종 특고압 보안공사",
      "③ 제2종 특고압 보안공사",
      "④ 제3종 특고압 보안공사"
    ]
  },
  {
    "number": 1,
    "question": "고주파 유전 가열에서 피열물의 단위 체적당 소비전력 W/cm³은? (단, E[V]㎝는 고주파 전계, δ는 유전체 손실각, f는 주파수, εs는 비유전율이다.)",
    "options": [
      "① 5/9 * E² * f * εs * tanδ * 10⁻⁸",
      "② 5/9 * E * f * εs * tanδ * 10⁻⁹",
      "③ 5/9 * E * f * εs * tanδ * 10⁻¹⁰",
      "④ 5/9 * E² * f * εs * tanδ * 10⁻¹²"
    ],
    "answer": 4,
    "pdf": "전기공사산업기사20160508(교사용).pdf",
    "page": 1,
    "round_info": "전기공사산업기사20160508(교사용)",
    "choices": [
      "① 5/9 * E² * f * εs * tanδ * 10⁻⁸",
      "② 5/9 * E * f * εs * tanδ * 10⁻⁹",
      "③ 5/9 * E * f * εs * tanδ * 10⁻¹⁰",
      "④ 5/9 * E² * f * εs * tanδ * 10⁻¹²"
    ]
  },
  {
    "number": 6,
    "question": "전기 가열의 특징에 해당되지 않는 것은?",
    "options": [
      "① 내부 가열이 가능하다.",
      "② 열효율이 매우 나쁘다.",
      "③ 방사열의 이용이 용이하다.",
      "④ 온도제어 및 조작이 간단하다."
    ],
    "answer": 2,
    "pdf": "전기공사산업기사20160508(교사용).pdf",
    "page": 1,
    "round_info": "전기공사산업기사20160508(교사용)",
    "choices": [
      "① 내부 가열이 가능하다.",
      "② 열효율이 매우 나쁘다.",
      "③ 방사열의 이용이 용이하다.",
      "④ 온도제어 및 조작이 간단하다."
    ]
  },
  {
    "number": 7,
    "question": "높이 10m의 곳에 있는 용량 100m³의 수조를 만수시키는데 필요한 전력량은 약 몇 kWh 인가? (단, 펌프의 종합 효율은 90%, 전손실 수두는 2m이다.)",
    "options": [
      "① 3.6",
      "② 4.1",
      "③ 7.2",
      "④ 8.9"
    ],
    "answer": 1,
    "pdf": "전기공사산업기사20160508(교사용).pdf",
    "page": 1,
    "round_info": "전기공사산업기사20160508(교사용)",
    "choices": [
      "① 3.6",
      "② 4.1",
      "③ 7.2",
      "④ 8.9"
    ]
  },
  {
    "number": 95,
    "question": "특고압 가공전선이 건조물과 1차 접근상태로 시설되는 경우를 설명한 것 중 틀린 것은?",
    "options": [
      "상부 조영재와 위쪽으로 접근 시 케이블을 사용하면 1.2m 이상 이격거리를 두어야 한다.",
      "상부 조영재와 옆쪽으로 접근 시 특고압 절연전선을 사용하면 1.5m 이상 이격거리를 두어야 한다.",
      "상부 조영재와 아래쪽으로 접근 시 특고압 절연전선을 사용하면 1.5m 이상 이격거리를 두어야 한다.",
      "상부 조영재와 위쪽으로 접근 시 특고압 절연전선을 사용하면 2.0m 이상 이격거리를 두어야 한다."
    ],
    "answer": 4,
    "pdf": "전기공사산업기사20160508(교사용).pdf",
    "page": 7,
    "round_info": "전기공사산업기사20160508(교사용)",
    "choices": [
      "상부 조영재와 위쪽으로 접근 시 케이블을 사용하면 1.2m 이상 이격거리를 두어야 한다.",
      "상부 조영재와 옆쪽으로 접근 시 특고압 절연전선을 사용하면 1.5m 이상 이격거리를 두어야 한다.",
      "상부 조영재와 아래쪽으로 접근 시 특고압 절연전선을 사용하면 1.5m 이상 이격거리를 두어야 한다.",
      "상부 조영재와 위쪽으로 접근 시 특고압 절연전선을 사용하면 2.0m 이상 이격거리를 두어야 한다."
    ]
  },
  {
    "number": 99,
    "question": "가반형의 용접전극을 사용하는 아크 용접장치의 용접 변압기의 1차측 전로의 대지전압은 몇 V 이하이어야 하는가?",
    "options": [
      "220",
      "300",
      "380",
      "440"
    ],
    "answer": 2,
    "pdf": "전기공사산업기사20160508(교사용).pdf",
    "page": 7,
    "round_info": "전기공사산업기사20160508(교사용)",
    "choices": [
      "220",
      "300",
      "380",
      "440"
    ]
  },
  {
    "number": 2,
    "question": "유전가열의 특징으로 틀린 것은?",
    "options": [
      "표면의 소손, 균열이 없다.",
      "온도 상승 속도가 빠르고 속도가 임의 제어된다.",
      "반도체의 정련, 단결정의 제조 등 특수 열처리가 가능하다.",
      "열이 유전체손에 의하여 피열물 자신에게 발생하므로 가열이 균일하다."
    ],
    "answer": 3,
    "pdf": "전기공사산업기사20161001(교사용).pdf",
    "page": 1,
    "round_info": "전기공사산업기사20161001(교사용)",
    "choices": [
      "표면의 소손, 균열이 없다.",
      "온도 상승 속도가 빠르고 속도가 임의 제어된다.",
      "반도체의 정련, 단결정의 제조 등 특수 열처리가 가능하다.",
      "열이 유전체손에 의하여 피열물 자신에게 발생하므로 가열이 균일하다."
    ]
  },
  {
    "number": 4,
    "question": "용접의 종류 중에서 저항용접이 아닌 것은?",
    "options": [
      "점 용접",
      "심 용접",
      "TIG 용접",
      "프로젝션 용접"
    ],
    "answer": 3,
    "pdf": "전기공사산업기사20161001(교사용).pdf",
    "page": 1,
    "round_info": "전기공사산업기사20161001(교사용)",
    "choices": [
      "점 용접",
      "심 용접",
      "TIG 용접",
      "프로젝션 용접"
    ]
  },
  {
    "number": 12,
    "question": "반경 3[cm], 두께 1[cm]의 강판을 유도가열에 의하여 3초 동안에 20[℃]에서 700[℃]로 상승시키기 위해 필요한 전력은 약 몇 [kW]인가?(단, 강판의 비중은 7.85[ton/m³], 비열은 0.16[kcal/kg·℃]이다.)",
    "options": [
      "3.37",
      "33.7",
      "6.67",
      "66.7"
    ],
    "answer": 2,
    "pdf": "전기공사산업기사20161001(교사용).pdf",
    "page": 1,
    "round_info": "전기공사산업기사20161001(교사용)",
    "choices": [
      "3.37",
      "33.7",
      "6.67",
      "66.7"
    ]
  },
  {
    "number": 2,
    "question": "목재 건조에 적합한 가열 방식은?",
    "options": [
      "저항 가열",
      "유전 가열",
      "유도 가열",
      "적외선 가열"
    ],
    "answer": 2,
    "pdf": "전기공사산업기사20170305(교사용).pdf",
    "page": 1,
    "round_info": "전기공사산업기사20170305(교사용)",
    "choices": [
      "저항 가열",
      "유전 가열",
      "유도 가열",
      "적외선 가열"
    ]
  },
  {
    "number": 11,
    "question": "전자빔 가열의 특징으로 틀린 것은?",
    "options": [
      "진공 중에서의 가열이 가능하다.",
      "신속하고 효율이 좋으며 표면 가열이 가능하다.",
      "고융점 재료 및 금속박 재료의 용접이 쉽다.",
      "에너지의 밀도나 분포를 자유로이 조절할 수 있다."
    ],
    "answer": 2,
    "pdf": "전기공사산업기사20170305(교사용).pdf",
    "page": 1,
    "round_info": "전기공사산업기사20170305(교사용)",
    "choices": [
      "진공 중에서의 가열이 가능하다.",
      "신속하고 효율이 좋으며 표면 가열이 가능하다.",
      "고융점 재료 및 금속박 재료의 용접이 쉽다.",
      "에너지의 밀도나 분포를 자유로이 조절할 수 있다."
    ]
  },
  {
    "number": 18,
    "question": "다음 중 전기로의 가열방식이 아닌 것은?",
    "options": [
      "저항 가열",
      "유전 가열",
      "유도 가열",
      "아크 가열"
    ],
    "answer": 2,
    "pdf": "전기공사산업기사20170305(교사용).pdf",
    "page": 1,
    "round_info": "전기공사산업기사20170305(교사용)",
    "choices": [
      "저항 가열",
      "유전 가열",
      "유도 가열",
      "아크 가열"
    ]
  },
  {
    "number": 6,
    "question": "다음 중 유도가열은 어떤 것을 이용한 것인가?",
    "options": [
      "복사열",
      "아크열",
      "와전류손",
      "유전체손"
    ],
    "answer": 3,
    "pdf": "전기공사산업기사20170507(교사용).pdf",
    "page": 1,
    "round_info": "전기공사산업기사20170507(교사용)",
    "choices": [
      "복사열",
      "아크열",
      "와전류손",
      "유전체손"
    ]
  },
  {
    "number": 7,
    "question": "기중기 등으로 물건을 내릴 때 또는 전차가 언덕을 내려가는 경우 전동기가 갖는 운동에너지를 전기에너지로 변환하고, 이것을 전원에 반환하면서 속도를 점차로 감속시키는 제동법은?",
    "options": [
      "발전제동",
      "회생제동",
      "역상제동",
      "와류제동"
    ],
    "answer": 2,
    "pdf": "전기공사산업기사20170507(교사용).pdf",
    "page": 1,
    "round_info": "전기공사산업기사20170507(교사용)",
    "choices": [
      "발전제동",
      "회생제동",
      "역상제동",
      "와류제동"
    ]
  },
  {
    "number": 11,
    "question": "전자빔 가열의 특징이 아닌 것은?",
    "options": [
      "에너지 밀도를 높게 할 수 있다.",
      "진공 중 가열로 산화 등의 영향이 크다.",
      "필요한 부분에 고속으로 가열시킬 수 있다.",
      "빔의 파워와 조사 위치를 정확히 제어할 수 있다."
    ],
    "answer": 2,
    "pdf": "전기공사산업기사20170507(교사용).pdf",
    "page": 1,
    "round_info": "전기공사산업기사20170507(교사용)",
    "choices": [
      "에너지 밀도를 높게 할 수 있다.",
      "진공 중 가열로 산화 등의 영향이 크다.",
      "필요한 부분에 고속으로 가열시킬 수 있다.",
      "빔의 파워와 조사 위치를 정확히 제어할 수 있다."
    ]
  },
  {
    "number": 6,
    "question": "발전소에 설치된 50[t]의 천장주행 기중기의 권상속도가 2[m/min]일 때 권상용 전동기의 용량은 약 몇 [kW]인가? (단, 효율은 70[%]이다.)",
    "options": [
      "5",
      "10",
      "15",
      "23"
    ],
    "answer": 4,
    "pdf": "전기공사산업기사20170923(교사용).pdf",
    "page": 1,
    "round_info": "전기공사산업기사20170923(교사용)",
    "choices": [
      "5",
      "10",
      "15",
      "23"
    ]
  },
  {
    "number": 12,
    "question": "무인 엘리베이터의 자동제어는?",
    "options": [
      "정치제어",
      "추종제어",
      "비율제어",
      "프로그램제어"
    ],
    "answer": 4,
    "pdf": "전기공사산업기사20170923(교사용).pdf",
    "page": 1,
    "round_info": "전기공사산업기사20170923(교사용)",
    "choices": [
      "정치제어",
      "추종제어",
      "비율제어",
      "프로그램제어"
    ]
  },
  {
    "number": 17,
    "question": "고주파 유도가열에 사용되는 전원이 아닌 것은?",
    "options": [
      "동기 발전기",
      "진공관 발전기",
      "고주파 전동발전기",
      "불꽃 간극식 고주파 발전기"
    ],
    "answer": 1,
    "pdf": "전기공사산업기사20170923(교사용).pdf",
    "page": 1,
    "round_info": "전기공사산업기사20170923(교사용)",
    "choices": [
      "동기 발전기",
      "진공관 발전기",
      "고주파 전동발전기",
      "불꽃 간극식 고주파 발전기"
    ]
  },
  {
    "number": 1,
    "question": "적외선 가열과 관계없는 것은?",
    "options": [
      "설비비가 적다.",
      "구조가 간단하다.",
      "두꺼운 목재의 건조에 적당하다.",
      "공산품(工産品)의 표면건조에 적당하다."
    ],
    "answer": 3,
    "pdf": "전기공사산업기사20180304(교사용).pdf",
    "page": 1,
    "round_info": "전기공사산업기사20180304(교사용)",
    "choices": [
      "설비비가 적다.",
      "구조가 간단하다.",
      "두꺼운 목재의 건조에 적당하다.",
      "공산품(工産品)의 표면건조에 적당하다."
    ]
  },
  {
    "number": 9,
    "question": "전압과 전류의 관계에서 수하특성을 이용한 가열 방식은?",
    "options": [
      "저항가열",
      "유도가열",
      "유전가열",
      "아크가열"
    ],
    "answer": 4,
    "pdf": "전기공사산업기사20180304(교사용).pdf",
    "page": 1,
    "round_info": "전기공사산업기사20180304(교사용)",
    "choices": [
      "저항가열",
      "유도가열",
      "유전가열",
      "아크가열"
    ]
  },
  {
    "number": 12,
    "question": "5층 빌딩에 설치된 적재중량 1000kg의 엘리베이터를 승강 속도 50m/min로 운전하기 위한 전동기의 출력은 약 몇 kW 인가? (단, 권상기의 기계효율은 0.9이고 균형추의 불평형률은 1이다.)",
    "options": [
      "4",
      "6",
      "7",
      "9"
    ],
    "answer": 4,
    "pdf": "전기공사산업기사20180304(교사용).pdf",
    "page": 1,
    "round_info": "전기공사산업기사20180304(교사용)",
    "choices": [
      "4",
      "6",
      "7",
      "9"
    ]
  },
  {
    "number": 1,
    "question": "전기가열 방식 중 전기적 절연물에 교번전계를 가할 때 물체 내부의 전기 쌍극자의 회전에 의해 발열하는 가열 방식은?",
    "options": [
      "저항 가열",
      "유도 가열",
      "유전 가열",
      "전자빔 가열"
    ],
    "answer": 3,
    "pdf": "전기공사산업기사20180428(교사용).pdf",
    "page": 1,
    "round_info": "전기공사산업기사20180428(교사용)",
    "choices": [
      "저항 가열",
      "유도 가열",
      "유전 가열",
      "전자빔 가열"
    ]
  },
  {
    "number": 8,
    "question": "양수량 5m³/min, 총양정 10m인 양수용 펌프 전동기의 용량은 약 몇 kW 인가? (단, 펌프 효율 85%, 여유계수 K=1.1이다.)",
    "options": [
      "9.01",
      "10.56",
      "16.60",
      "17.66"
    ],
    "answer": 2,
    "pdf": "전기공사산업기사20180428(교사용).pdf",
    "page": 1,
    "round_info": "전기공사산업기사20180428(교사용)",
    "choices": [
      "9.01",
      "10.56",
      "16.60",
      "17.66"
    ]
  },
  {
    "number": 9,
    "question": "적외선 건조에 대한 설명으로 틀린 것은?",
    "options": [
      "효율이 좋다.",
      "온도 조절이 쉽다.",
      "대류열을 이용한다.",
      "소요되는 면적이 작다."
    ],
    "answer": 3,
    "pdf": "전기공사산업기사20180428(교사용).pdf",
    "page": 1,
    "round_info": "전기공사산업기사20180428(교사용)",
    "choices": [
      "효율이 좋다.",
      "온도 조절이 쉽다.",
      "대류열을 이용한다.",
      "소요되는 면적이 작다."
    ]
  },
  {
    "number": 20,
    "question": "저항 용접에 속하지 않는 것은?",
    "options": [
      "심 용접",
      "아크 용접",
      "스폿 용접",
      "프로젝션 용접"
    ],
    "answer": 2,
    "pdf": "전기공사산업기사20180428(교사용).pdf",
    "page": 1,
    "round_info": "전기공사산업기사20180428(교사용)",
    "choices": [
      "심 용접",
      "아크 용접",
      "스폿 용접",
      "프로젝션 용접"
    ]
  },
  {
    "number": 3,
    "question": "용해, 용접, 담금질, 가열 등에 가장 적합한 가열방식은?",
    "options": [
      "복사가열",
      "유도가열",
      "저항가열",
      "유전가열"
    ],
    "answer": 2,
    "pdf": "전기공사산업기사20180915(교사용).pdf",
    "page": 1,
    "round_info": "전기공사산업기사20180915(교사용)",
    "choices": [
      "복사가열",
      "유도가열",
      "저항가열",
      "유전가열"
    ]
  },
  {
    "number": 12,
    "question": "고주파 유전가열에서 피열물의 단위 체적당 소비전력 [W/cm³]은? (단, E[V/cm]는 고주파 전계, δ는 유전체 손실각, f는 주파수, εₛ는 비유전율이다.)",
    "options": [
      "5/9 * E * f * εs * tanδ * 10^-9",
      "5/9 * E * f * εs * tanδ * 10^-10",
      "5/9 * E * f * εs * tanδ * 10^-8",
      "5/9 * E * f * εs * tanδ * 10^-12"
    ],
    "answer": 4,
    "pdf": "전기공사산업기사20180915(교사용).pdf",
    "page": 1,
    "round_info": "전기공사산업기사20180915(교사용)",
    "choices": [
      "5/9 * E * f * εs * tanδ * 10^-9",
      "5/9 * E * f * εs * tanδ * 10^-10",
      "5/9 * E * f * εs * tanδ * 10^-8",
      "5/9 * E * f * εs * tanδ * 10^-12"
    ]
  },
  {
    "number": 16,
    "question": "플라즈마 용접의 특징이 아닌 것은?",
    "options": [
      "비드(bead)폭이 좁고 용입이 깊다.",
      "용접속도가 빠르고 균일한 용접이 된다.",
      "가스의 보호가 충분하여, 토치의 구조가 간단하다.",
      "플라즈마 아크의 에너지 밀도가 커서 안정도가 커서 안정도가 높다."
    ],
    "answer": 3,
    "pdf": "전기공사산업기사20180915(교사용).pdf",
    "page": 1,
    "round_info": "전기공사산업기사20180915(교사용)",
    "choices": [
      "비드(bead)폭이 좁고 용입이 깊다.",
      "용접속도가 빠르고 균일한 용접이 된다.",
      "가스의 보호가 충분하여, 토치의 구조가 간단하다.",
      "플라즈마 아크의 에너지 밀도가 커서 안정도가 커서 안정도가 높다."
    ]
  },
  {
    "number": 3,
    "question": "전기가열 방식에 대한 설명으로 틀린 것은?",
    "options": [
      "저항가열은 줄열을 이용한 가열방식이다.",
      "유도가열은 표면 담금질 등의 열처리에 이용되는 방식이다.",
      "유전가열은 와전류손과 히스테리시스손에 의한 가열방식이다.",
      "아크가열은 전극사이에 발생하는 아크열을 이용한 가열방식이다."
    ],
    "answer": 3,
    "year": "2019",
    "pdf": "전기공사산업기사20190303(교사용).pdf",
    "page": 1,
    "round_info": "전기공사산업기사20190303(교사용)",
    "choices": [
      "저항가열은 줄열을 이용한 가열방식이다.",
      "유도가열은 표면 담금질 등의 열처리에 이용되는 방식이다.",
      "유전가열은 와전류손과 히스테리시스손에 의한 가열방식이다.",
      "아크가열은 전극사이에 발생하는 아크열을 이용한 가열방식이다."
    ]
  },
  {
    "number": 4,
    "question": "엘리베이터용 전동기에 대한 설명으로 틀린 것은?",
    "options": [
      "관성모멘트가 작아야 한다.",
      "기동토크가 큰 것이 요구된다.",
      "플라이휠 효과($GD^2$)가 커야 한다.",
      "가속도의 변화율이 적어야 한다."
    ],
    "answer": 3,
    "year": "2019",
    "pdf": "전기공사산업기사20190303(교사용).pdf",
    "page": 1,
    "round_info": "전기공사산업기사20190303(교사용)",
    "choices": [
      "관성모멘트가 작아야 한다.",
      "기동토크가 큰 것이 요구된다.",
      "플라이휠 효과($GD^2$)가 커야 한다.",
      "가속도의 변화율이 적어야 한다."
    ]
  },
  {
    "number": 8,
    "question": "유도가열과 유전가열의 공통된 특성은?",
    "options": [
      "도체만을 가열한다.",
      "선택가열이 가능하다.",
      "절연체만을 가열한다.",
      "직류를 사용할 수 없다."
    ],
    "answer": 4,
    "year": "2019",
    "pdf": "전기공사산업기사20190303(교사용).pdf",
    "page": 1,
    "round_info": "전기공사산업기사20190303(교사용)",
    "choices": [
      "도체만을 가열한다.",
      "선택가열이 가능하다.",
      "절연체만을 가열한다.",
      "직류를 사용할 수 없다."
    ]
  },
  {
    "number": 11,
    "question": "고주파 유전가열을 응용한 사항으로 틀린 것은?",
    "options": [
      "고무의 가황",
      "합판의 건조, 접착",
      "플라스틱의 성형과 비닐막 접착",
      "강재의 표면 담금질"
    ],
    "answer": 4,
    "year": "2019",
    "pdf": "전기공사산업기사20190303(교사용).pdf",
    "page": 1,
    "round_info": "전기공사산업기사20190303(교사용)",
    "choices": [
      "고무의 가황",
      "합판의 건조, 접착",
      "플라스틱의 성형과 비닐막 접착",
      "강재의 표면 담금질"
    ]
  },
  {
    "number": 81,
    "question": "중선선 다중접지식의 것으로 전로에 지락이 생겼을 때에 2초 이내에 자동적으로 이를 전로로부터 차단하는 장치가 되어 있는 $22.9 kV$ 가공전선로를 상부 조영재의 위쪽에서 접근상태로 시설하는 경우, 가공전선과 건조물과의 이격거리는 몇 $m$ 이상이어야 하는가? (단, 전선으로는 나전선을 사용한다고 한다.)",
    "options": [
      "1.2",
      "1.5",
      "2.5",
      "3.0"
    ],
    "answer": 4,
    "year": "2019",
    "pdf": "전기공사산업기사20190303(교사용).pdf",
    "page": 6,
    "round_info": "전기공사산업기사20190303(교사용)",
    "choices": [
      "1.2",
      "1.5",
      "2.5",
      "3.0"
    ]
  },
  {
    "number": 87,
    "question": "건조한 장소로서 전개된 장소에 한하여 시설할 수 있는 고압 옥내배선의 방법은?",
    "options": [
      "금속관 공사",
      "애자사용 공사",
      "가요전선관 공사",
      "합성수지관 공사"
    ],
    "answer": 2,
    "year": "2019",
    "pdf": "전기공사산업기사20190303(교사용).pdf",
    "page": 6,
    "round_info": "전기공사산업기사20190303(교사용)",
    "choices": [
      "금속관 공사",
      "애자사용 공사",
      "가요전선관 공사",
      "합성수지관 공사"
    ]
  },
  {
    "number": 10,
    "question": "교번 자계 중에서 도전성 물질 내에 생기는 와류손과 히스테리시스손에 의한 가열 방식은?",
    "options": [
      "저항가열",
      "유도가열",
      "유전가열",
      "아크가열"
    ],
    "answer": 2,
    "year": "2019",
    "pdf": "전기공사산업기사20190427(교사용).pdf",
    "page": 1,
    "round_info": "전기공사산업기사20190427(교사용)",
    "choices": [
      "저항가열",
      "유도가열",
      "유전가열",
      "아크가열"
    ]
  },
  {
    "number": 14,
    "question": "동력 전달 효율이 $78.4\\%$인 권상기로 $30\\text{t}$의 하중을 매분 $4\\text{m}$의 속도로 끌어 올리는 데 필요한 동력은 약 몇 $\\text{kW}$인가?",
    "options": [
      "14",
      "18",
      "21",
      "25"
    ],
    "answer": 4,
    "year": "2019",
    "pdf": "전기공사산업기사20190427(교사용).pdf",
    "page": 1,
    "round_info": "전기공사산업기사20190427(교사용)",
    "choices": [
      "14",
      "18",
      "21",
      "25"
    ]
  },
  {
    "number": 3,
    "question": "고주파 유전가열의 용도로 적합하지 않은 것은?",
    "options": [
      "목재의 접착",
      "플라스틱 성형",
      "비닐의 접착",
      "금속의 열처리"
    ],
    "answer": 4,
    "year": "2019",
    "pdf": "전기공사산업기사20190921(교사용).pdf",
    "page": 1,
    "round_info": "전기공사산업기사20190921(교사용)",
    "choices": [
      "목재의 접착",
      "플라스틱 성형",
      "비닐의 접착",
      "금속의 열처리"
    ]
  },
  {
    "number": 38,
    "question": "출력 20kW의 전동기로서 총 양정 10m, 펌프효율 0.75일 때 양수량은 약 몇 $m^3/min$ 인가?",
    "options": [
      "9.18",
      "9.85",
      "10.31",
      "11.02"
    ],
    "answer": 1,
    "year": "2019",
    "pdf": "전기공사산업기사20190921(교사용).pdf",
    "page": 3,
    "round_info": "전기공사산업기사20190921(교사용)",
    "choices": [
      "9.18",
      "9.85",
      "10.31",
      "11.02"
    ]
  },
  {
    "number": 90,
    "question": "$66kV$ 가공전선이 건조물과 제1차 접근상태로 시설되는 경우 가공전선과 건조물 사이의 이격거리는 최소 몇 $m$ 이상이어야 하는가? (단, 전선은 나전선으로 한다.)",
    "options": [
      "3.0",
      "3.2",
      "3.4",
      "3.6"
    ],
    "answer": 4,
    "year": "2019",
    "pdf": "전기공사산업기사20190921(교사용).pdf",
    "page": 6,
    "round_info": "전기공사산업기사20190921(교사용)",
    "choices": [
      "3.0",
      "3.2",
      "3.4",
      "3.6"
    ]
  },
  {
    "number": 5,
    "question": "다음 중 유도가열은 어떤 것을 이용한 것인가?",
    "options": [
      "복사열",
      "아크열",
      "와전류손",
      "유전체손"
    ],
    "answer": 3,
    "year": "2020",
    "pdf": "전기공사산업기사20200606(교사용).pdf",
    "page": 1,
    "round_info": "전기공사산업기사20200606(교사용)",
    "choices": [
      "복사열",
      "아크열",
      "와전류손",
      "유전체손"
    ]
  },
  {
    "number": 13,
    "question": "방전용접 중 불활성 가스용접에 쓰이는 불활성 가스는?",
    "options": [
      "아르곤",
      "수소",
      "산소",
      "질소"
    ],
    "answer": 1,
    "year": "2020",
    "pdf": "전기공사산업기사20200606(교사용).pdf",
    "page": 1,
    "round_info": "전기공사산업기사20200606(교사용)",
    "choices": [
      "아르곤",
      "수소",
      "산소",
      "질소"
    ]
  },
  {
    "number": 19,
    "question": "목재의 건조, 베니어판 등의 합판에서의 접착 건조, 약품의 건조 등에 적합한 전기 건조 방식은?",
    "options": [
      "아크 건조",
      "고주파 건조",
      "적외선 건조",
      "자외선 건조"
    ],
    "answer": 2,
    "year": "2020",
    "pdf": "전기공사산업기사20200606(교사용).pdf",
    "page": 1,
    "round_info": "전기공사산업기사20200606(교사용)",
    "choices": [
      "아크 건조",
      "고주파 건조",
      "적외선 건조",
      "자외선 건조"
    ]
  },
  {
    "number": 3,
    "question": "목재건조에 적합한 가열 방식은?",
    "options": [
      "저항가열",
      "적외선 가열",
      "유전가열",
      "유도가열"
    ],
    "answer": 3,
    "year": "2020",
    "pdf": "전기공사산업기사20200822(교사용).pdf",
    "page": 1,
    "round_info": "전기공사산업기사20200822(교사용)",
    "choices": [
      "저항가열",
      "적외선 가열",
      "유전가열",
      "유도가열"
    ]
  },
  {
    "number": 12,
    "question": "초음파 용접의 특징으로 옳지 않은 것은?",
    "options": [
      "전기 저항 용접에 비하여 표면의 전처리가 간단하다.",
      "가열을 필요로 하지 않는다.",
      "냉간 압접 등에 비하여 접합부 표면의 변형이 적다.",
      "고체상태에서의 용접이므로 열적 영향이 크다."
    ],
    "answer": 4,
    "year": "2020",
    "pdf": "전기공사산업기사20200822(교사용).pdf",
    "page": 1,
    "round_info": "전기공사산업기사20200822(교사용)",
    "choices": [
      "전기 저항 용접에 비하여 표면의 전처리가 간단하다.",
      "가열을 필요로 하지 않는다.",
      "냉간 압접 등에 비하여 접합부 표면의 변형이 적다.",
      "고체상태에서의 용접이므로 열적 영향이 크다."
    ]
  },
  {
    "number": 16,
    "question": "평행평판 전극 사이에 유전체인 피열물을 삽입하고 고주파 전계를 인가하면 피열물 내 유전체손이 발생하여 가열되는 방식은?",
    "options": [
      "저항가열",
      "유도가열",
      "유전가열",
      "원자수소가열"
    ],
    "answer": 3,
    "year": "2020",
    "pdf": "전기공사산업기사20200822(교사용).pdf",
    "page": 1,
    "round_info": "전기공사산업기사20200822(교사용)",
    "choices": [
      "저항가열",
      "유도가열",
      "유전가열",
      "원자수소가열"
    ]
  },
  {
    "number": 17,
    "question": "권상하중 10t, 매분 24m/min의 속도로 물체를 올리는 권상용 전동기의 용량(kW)은 약 얼마인가? (단, 전동기를 포함한 기중기의 효율은 65%이다.)",
    "options": [
      "41",
      "73",
      "60",
      "97"
    ],
    "answer": 3,
    "year": "2020",
    "pdf": "전기공사산업기사20200822(교사용).pdf",
    "page": 1,
    "round_info": "전기공사산업기사20200822(교사용)",
    "choices": [
      "41",
      "73",
      "60",
      "97"
    ]
  }
]